fingerprint_browser/__init__.py
fingerprint_browser/hubstudio.py
fingerprint_browser/utils.py
fpb-0.6.dist-info/METADATA
fpb-0.6.dist-info/WHEEL
fpb-0.6.dist-info/top_level.txt
fpb-0.6.dist-info/RECORD
