Metadata-Version: 2.1
Name: fpb
Version: 0.6
Author: Alex
Author-email: 2831926323@qq.com
Requires-Dist: aiohttp
Requires-Dist: psutil
Requires-Dist: inflection
